commonmeta/__init__.py
commonmeta/api_utils.py
commonmeta/author_utils.py
commonmeta/base_utils.py
commonmeta/cli.py
commonmeta/constants.py
commonmeta/date_utils.py
commonmeta/doi_utils.py
commonmeta/file_utils.py
commonmeta/metadata.py
commonmeta/schema_utils.py
commonmeta/translators.py
commonmeta/utils.py
commonmeta/readers/__init__.py
commonmeta/readers/bibtex_reader.py
commonmeta/readers/cff_reader.py
commonmeta/readers/codemeta_reader.py
commonmeta/readers/commonmeta_reader.py
commonmeta/readers/crossref_reader.py
commonmeta/readers/crossref_xml_reader.py
commonmeta/readers/csl_reader.py
commonmeta/readers/datacite_reader.py
commonmeta/readers/datacite_xml_reader.py
commonmeta/readers/inveniordm_reader.py
commonmeta/readers/jsonfeed_reader.py
commonmeta/readers/kbase_reader.py
commonmeta/readers/openalex_reader.py
commonmeta/readers/ris_reader.py
commonmeta/readers/schema_org_reader.py
commonmeta/resources/cff_v1.2.0.json
commonmeta/resources/commonmeta_v0.12.json
commonmeta/resources/commonmeta_v0.13.json
commonmeta/resources/commonmeta_v0.14.json
commonmeta/resources/commonmeta_v0.15.json
commonmeta/resources/commonmeta_v0.16.json
commonmeta/resources/commonmeta_v0.17.json
commonmeta/resources/crossref-v0.2.json
commonmeta/resources/csl-data.json
commonmeta/resources/datacite-v4.5.json
commonmeta/resources/datacite-v4.5pr.json
commonmeta/resources/inveniordm-v0.1.json
commonmeta/resources/schema_org-v0.1.json
commonmeta/resources/spdx-schema.json
commonmeta/resources/crossref/AccessIndicators.xsd
commonmeta/resources/crossref/JATS-journalpublishing1-3d2-mathml3-elements.xsd
commonmeta/resources/crossref/JATS-journalpublishing1-3d2-mathml3.xsd
commonmeta/resources/crossref/JATS-journalpublishing1-elements.xsd
commonmeta/resources/crossref/JATS-journalpublishing1-mathml3-elements.xsd
commonmeta/resources/crossref/JATS-journalpublishing1-mathml3.xsd
commonmeta/resources/crossref/JATS-journalpublishing1.xsd
commonmeta/resources/crossref/clinicaltrials.xsd
commonmeta_py-0.199.dist-info/METADATA
commonmeta_py-0.199.dist-info/WHEEL
commonmeta_py-0.199.dist-info/entry_points.txt
commonmeta_py-0.199.dist-info/licenses/LICENSE
commonmeta_py-0.199.dist-info/RECORD
