Metadata-Version: 2.4
Name: commonmeta-py
Version: 0.199
Summary: Library for conversions to/from the Commonmeta scholarly metadata format
Project-URL: Homepage, https://python.commonmeta.org
Project-URL: Repository, https://github.com/front-matter/commonmeta-py
Project-URL: Documentation, https://python.commonmeta.org
Author-email: Martin Fenner <martin@front-matter.de>
License: MIT
License-File: LICENSE
Keywords: bibtex,commonmeta,crossref,csl,datacite,inveniordm,metadata,openalex,schemaorg,science
Requires-Python: <4.0,>=3.10
Requires-Dist: base32-lib~=1.0
Requires-Dist: beautifulsoup4<5,>=4.11
Requires-Dist: bibtexparser~=1.4
Requires-Dist: citeproc-py-styles<1,>=0.1.2
Requires-Dist: citeproc-py<1,>=0.6
Requires-Dist: click<9,>=8.1.7
Requires-Dist: datacite<2,>=1.1.1
Requires-Dist: dateparser<2,>=1.1.7
Requires-Dist: edtf<6,>=5.0.0
Requires-Dist: furl<3,>=2.1.3
Requires-Dist: isbnlib>=3.10.14
Requires-Dist: jsonschema~=4.21
Requires-Dist: lxml>=4.8
Requires-Dist: marshmallow-utils>=0.10.0
Requires-Dist: nameparser<2,>=1.1.1
Requires-Dist: nh3<0.3,>=0.2.14
Requires-Dist: orjson<4,>=3.9.14
Requires-Dist: orjsonl<2,>=1.0.0
Requires-Dist: pycountry>=22.3.5
Requires-Dist: pyjwt<3,>=2.8.0
Requires-Dist: python-dateutil<3,>=2.8.2
Requires-Dist: pyyaml>=5.4
Requires-Dist: requests-toolbelt>=1.0.0
Requires-Dist: requests>=2.31.0
Requires-Dist: requests>=2.32.3
Requires-Dist: types-beautifulsoup4<5,>=4.11
Requires-Dist: types-dateparser~=1.1
Requires-Dist: types-pyyaml>=5.4
Requires-Dist: types-xmltodict<0.20,>=0.13
Requires-Dist: xmlschema>=4.0.1
Requires-Dist: xmltodict<0.20,>=0.12
